Workbook

Sheet Cover
B2: BREAKWATER CAPITAL PARTNERS
B5: Special Situations Development Platform
B6: Single-Asset Underwriting Model
B9: PURPOSE
B10: Underwrites one distressed luxury-residential completion opportunity from
B11: distressed basis to exit. Solve for the completion spread, the equity check,
B12: project IRR, and the partner-level waterfall — then stress-test the result.
B14: HOW TO USE
B15: 1. Edit only the yellow cells on the INPUTS tab.
B16: 2. UNDERWRITING, RETURNS, and SENSITIVITY recalculate automatically.
B17: 3. Confirm the deal clears the thresholds (see methodology doc).
B19: DECISION THRESHOLDS (must all hold to proceed)
... B27: Illustrative only. Not investment advice; not a guarantee of results.

Sheet Inputs
A1: INPUTS — edit the yellow cells only
C2: Source / discipline
A4: Finished (exit) value | B4: 7500000 | C4: ≥3 finished comps; brokerage-validated; time haircut
A5: Acquisition cost (control) | B5: 3700000 | C5: Solved from screen + max-basis, not the ask
A6: Acquisition closing % | B6: 0.02 | C6: Title, legal, transfer; in-house where possible
A7: Cost to complete (hard+soft) | B7: 1400000 | C7: Independent estimate; scope-verified
A8: Contingency % | B8: 0.12 | C8: 10% base / 12–15% complex or stale budget
A9: Hold period (months) | B9: 12 | C9: Construction + listing + closing lag; honest
A10: Monthly carry | B10: 15000 | C10: Taxes + insurance + utilities/security + admin
A11: Disposition cost % | B11: 0.05 | C11: Commission + closing + concessions
A12: Loan amount (debt) | B12: 4800000 | C12: Per term sheet; preserve refi optionality
A13: Loan rate (annual) | B13: 0.1 | C13: Acquisition / completion financing
A14: Origination / fees % | B14: 0.015 | C14: Points + lender fees
A15: Preferred return (annual) | B15: 0.09 | C15: Hurdle to capital partners before promote
A16: Promote (GP share over pref) | B16: 0.2 | C16: GP share of residual profit

Sheet Underwriting
A1: UNDERWRITING — all-in basis, spread & project return
A3: PROJECT COSTS (asset-level, unlevered)
A4: Acquisition cost (control) | B4: =Inputs!$B$5
A5: Acquisition closing costs | B5: =Inputs!$B$5*Inputs!$B$6
A6: Cost to complete (hard+soft) | B6: =Inputs!$B$7
A7: Contingency | B7: =Inputs!$B$7*Inputs!$B$8
A8: Carry costs over hold | B8: =Inputs!$B$10*Inputs!$B$9
A9: Disposition costs | B9: =Inputs!$B$4*Inputs!$B$11
A10: ALL-IN BASIS (asset-level) | B10: =SUM(B4:B9)
A12: COMPLETION SPREAD
A13: Finished (exit) value | B13: =Inputs!$B$4
A14: Completion spread ($) | B14: =Inputs!$B$4-B10
A15: Completion spread (%) | B15: =B14/B10
A17: FINANCING
A18: Interest (IO over hold) | B18: =Inputs!$B$12*Inputs!$B$13*Inputs!$B$9/12
A19: Origination / fees | B19: =Inputs!$B$12*Inputs!$B$14
A20: Total financing cost | B20: =B18+B19
A22: SOURCES & USES / EQUITY
A23: Total uses (basis + financing) | B23: =B10+B20
A24: Less: loan (debt) | B24: =-Inputs!$B$12
A25: EQUITY REQUIRED | B25: =B23-Inputs!$B$12
A27: PROJECT RETURN (to equity)
A28: Net sale proceeds (FV − disposition) | B28: =Inputs!$B$4-Inputs!$B$4*Inputs!$B$11
A29: Equity proceeds at exit (net − loan) | B29: =B28-Inputs!$B$12
A30: PROJECT PROFIT | B30: =B29-B25
A31: Equity multiple (gross) | B31: =B29/B25
A32: Annualized return (approx IRR) | B32: =(B29/B25)^(12/Inputs!$B$9)-1
A34: THRESHOLD CHECK
A35: Spread ≥ 20% ? | B35: =IF(B15>=0.2,"PASS","REVIEW")
A36: Equity multiple ≥ 1.35x ? | B36: =IF(B31>=1.35,"PASS","REVIEW")
A37: IRR ≥ 20% ? | B37: =IF(B32>=0.2,"PASS","REVIEW")

Sheet Returns
A1: RETURNS — partner waterfall (deal-by-deal)
A3: DISTRIBUTION WATERFALL
A4: Invested equity (capital partners) | B4: =Underwriting!$B$25
A5: Total distributable (equity proceeds) | B5: =Underwriting!$B$29
A6: Preferred return accrued | B6: =Underwriting!$B$25*Inputs!$B$15*Inputs!$B$9/12
A7: Project profit | B7: =Underwriting!$B$30
A9: TIERED SPLIT
A10: 1. Return of capital → LP | B10: =MIN(B5,B4)
A11: 2. Preferred return → LP | B11: =MIN(B7,B6)
A12: Residual after pref | B12: =MAX(B7-B6,0)
A13: 3. Promote → GP | B13: =B12*Inputs!$B$16
A14: 4. Residual split → LP | B14: =B12*(1-Inputs!$B$16)
A16: PARTNER OUTCOMES
A17: LP total distribution | B17: =B10+B11+B14
A18: LP profit | B18: =B11+B14
A19: LP equity multiple | B19: =B17/B4
A20: LP annualized return | B20: =(B17/B4)^(12/Inputs!$B$9)-1
A21: GP profit (promote) | B21: =B13
A23: GP also co-invests alongside LPs on every deal (not modeled here).

Sheet Sensitivity
A1: SENSITIVITY — finished value × cost to complete
A3: PROJECT PROFIT (asset-level)
B4: Finished value →
A5: Cost to complete ↓ | B5: -0.1 | C5: -0.05 | D5: 0 | E5: 0.05 | F5: 0.1
A6: -0.1 | B6: =(Inputs!$B$4*0.9)-(Inputs!$B$5+Inputs!$B$5*Inputs!$B$6+(Inputs!$B$7*0.9)+(Inputs!$B$7*0.9)*Inputs!$B$8+Inputs!$B$10*Inputs!$B$9+(Inputs!$B$4*0.9)*Inputs!$B$11)-(Inputs!$B$12*Inputs!$B$13*Inputs!$B$9/12+Inputs!$B$12*Inputs!$B$14) | C6: =(Inputs!$B$4*0.95)-(Inputs!$B$5+Inputs!$B$5*Inputs!$B$6+(Inputs!$B$7*0.9)+(Inputs!$B$7*0.9)*Inputs!$B$8+Inputs!$B$10*Inputs!$B$9+(Inputs!$B$4*0.95)*Inputs!$B$11)-(Inputs!$B$12*Inputs!$B$13*Inputs!$B$9/12+Inputs!$B$12*Inputs!$B$14) | D6: =(Inputs!$B$4*1.0)-(Inputs!$B$5+Inputs!$B$5*Inputs!$B$6+(Inputs!$B$7*0.9)+(Inputs!$B$7*0.9)*Inputs!$B$8+Inputs!$B$10*Inputs!$B$9+(Inputs!$B$4*1.0)*Inputs!$B$11)-(Inputs!$B$12*Inputs!$B$13*Inputs!$B$9/12+Inputs!$B$12*Inputs!$B$14) | E6: =(Inputs!$B$4*1.05)-(Inputs!$B$5+Inputs!$B$5*Inputs!$B$6+(Inputs!$B$7*0.9)+(Inputs!$B$7*0.9)*Inputs!$B$8+Inputs!$B$10*Inputs!$B$9+(Inputs!$B$4*1.05)*Inputs!$B$11)-(Inputs!$B$12*Inputs!$B$13*Inputs!$B$9/12+Inputs!$B$12*Inputs!$B$14) | F6: =(Inputs!$B$4*1.1)-(Inputs!$B$5+Inputs!$B$5*Inputs!$B$6+(Inputs!$B$7*0.9)+(Inputs!$B$7*0.9)*Inputs!$B$8+Inputs!$B$10*Inputs!$B$9+(Inputs!$B$4*1.1)*Inputs!$B$11)-(Inputs!$B$12*Inputs!$B$13*Inputs!$B$9/12+Inputs!$B$12*Inputs!$B$14)
A7: 0 | B7: =(Inputs!$B$4*0.9)-(Inputs!$B$5+Inputs!$B$5*Inputs!$B$6+(Inputs!$B$7*1.0)+(Inputs!$B$7*1.0)*Inputs!$B$8+Inputs!$B$10*Inputs!$B$9+(Inputs!$B$4*0.9)*Inputs!$B$11)-(Inputs!$B$12*Inputs!$B$13*Inputs!$B$9/12+Inputs!$B$12*Inputs!$B$14) | C7: =(Inputs!$B$4*0.95)-(Inputs!$B$5+Inputs!$B$5*Inputs!$B$6+(Inputs!$B$7*1.0)+(Inputs!$B$7*1.0)*Inputs!$B$8+Inputs!$B$10*Inputs!$B$9+(Inputs!$B$4*0.95)*Inputs!$B$11)-(Inputs!$B$12*Inputs!$B$13*Inputs!$B$9/12+Inputs!$B$12*Inputs!$B$14) | D7: =(Inputs!$B$4*1.0)-(Inputs!$B$5+Inputs!$B$5*Inputs!$B$6+(Inputs!$B$7*1.0)+(Inputs!$B$7*1.0)*Inputs!$B$8+Inputs!$B$10*Inputs!$B$9+(Inputs!$B$4*1.0)*Inputs!$B$11)-(Inputs!$B$12*Inputs!$B$13*Inputs!$B$9/12+Inputs!$B$12*Inputs!$B$14) | E7: =(Inputs!$B$4*1.05)-(Inputs!$B$5+Inputs!$B$5*Inputs!$B$6+(Inputs!$B$7*1.0)+(Inputs!$B$7*1.0)*Inputs!$B$8+Inputs!$B$10*Inputs!$B$9+(Inputs!$B$4*1.05)*Inputs!$B$11)-(Inputs!$B$12*Inputs!$B$13*Inputs!$B$9/12+Inputs!$B$12*Inputs!$B$14) | F7: =(Inputs!$B$4*1.1)-(Inputs!$B$5+Inputs!$B$5*Inputs!$B$6+(Inputs!$B$7*1.0)+(Inputs!$B$7*1.0)*Inputs!$B$8+Inputs!$B$10*Inputs!$B$9+(Inputs!$B$4*1.1)*Inputs!$B$11)-(Inputs!$B$12*Inputs!$B$13*Inputs!$B$9/12+Inputs!$B$12*Inputs!$B$14)
A8: 0.1 | B8: =(Inputs!$B$4*0.9)-(Inputs!$B$5+Inputs!$B$5*Inputs!$B$6+(Inputs!$B$7*1.1)+(Inputs!$B$7*1.1)*Inputs!$B$8+Inputs!$B$10*Inputs!$B$9+(Inputs!$B$4*0.9)*Inputs!$B$11)-(Inputs!$B$12*Inputs!$B$13*Inputs!$B$9/12+Inputs!$B$12*Inputs!$B$14) | C8: =(Inputs!$B$4*0.95)-(Inputs!$B$5+Inputs!$B$5*Inputs!$B$6+(Inputs!$B$7*1.1)+(Inputs!$B$7*1.1)*Inputs!$B$8+Inputs!$B$10*Inputs!$B$9+(Inputs!$B$4*0.95)*Inputs!$B$11)-(Inputs!$B$12*Inputs!$B$13*Inputs!$B$9/12+Inputs!$B$12*Inputs!$B$14) | D8: =(Inputs!$B$4*1.0)-(Inputs!$B$5+Inputs!$B$5*Inputs!$B$6+(Inputs!$B$7*1.1)+(Inputs!$B$7*1.1)*Inputs!$B$8+Inputs!$B$10*Inputs!$B$9+(Inputs!$B$4*1.0)*Inputs!$B$11)-(Inputs!$B$12*Inputs!$B$13*Inputs!$B$9/12+Inputs!$B$12*Inputs!$B$14) | E8: =(Inputs!$B$4*1.05)-(Inputs!$B$5+Inputs!$B$5*Inputs!$B$6+(Inputs!$B$7*1.1)+(Inputs!$B$7*1.1)*Inputs!$B$8+Inputs!$B$10*Inputs!$B$9+(Inputs!$B$4*1.05)*Inputs!$B$11)-(Inputs!$B$12*Inputs!$B$13*Inputs!$B$9/12+Inputs!$B$12*Inputs!$B$14) | F8: =(Inputs!$B$4*1.1)-(Inputs!$B$5+Inputs!$B$5*Inputs!$B$6+(Inputs!$B$7*1.1)+(Inputs!$B$7*1.1)*Inputs!$B$8+Inputs!$B$10*Inputs!$B$9+(Inputs!$B$4*1.1)*Inputs!$B$11)-(Inputs!$B$12*Inputs!$B$13*Inputs!$B$9/12+Inputs!$B$12*Inputs!$B$14)
A9: 0.2 | B9: =(Inputs!$B$4*0.9)-(Inputs!$B$5+Inputs!$B$5*Inputs!$B$6+(Inputs!$B$7*1.2)+(Inputs!$B$7*1.2)*Inputs!$B$8+Inputs!$B$10*Inputs!$B$9+(Inputs!$B$4*0.9)*Inputs!$B$11)-(Inputs!$B$12*Inputs!$B$13*Inputs!$B$9/12+Inputs!$B$12*Inputs!$B$14) | C9: =(Inputs!$B$4*0.95)-(Inputs!$B$5+Inputs!$B$5*Inputs!$B$6+(Inputs!$B$7*1.2)+(Inputs!$B$7*1.2)*Inputs!$B$8+Inputs!$B$10*Inputs!$B$9+(Inputs!$B$4*0.95)*Inputs!$B$11)-(Inputs!$B$12*Inputs!$B$13*Inputs!$B$9/12+Inputs!$B$12*Inputs!$B$14) | D9: =(Inputs!$B$4*1.0)-(Inputs!$B$5+Inputs!$B$5*Inputs!$B$6+(Inputs!$B$7*1.2)+(Inputs!$B$7*1.2)*Inputs!$B$8+Inputs!$B$10*Inputs!$B$9+(Inputs!$B$4*1.0)*Inputs!$B$11)-(Inputs!$B$12*Inputs!$B$13*Inputs!$B$9/12+Inputs!$B$12*Inputs!$B$14) | E9: =(Inputs!$B$4*1.05)-(Inputs!$B$5+Inputs!$B$5*Inputs!$B$6+(Inputs!$B$7*1.2)+(Inputs!$B$7*1.2)*Inputs!$B$8+Inputs!$B$10*Inputs!$B$9+(Inputs!$B$4*1.05)*Inputs!$B$11)-(Inputs!$B$12*Inputs!$B$13*Inputs!$B$9/12+Inputs!$B$12*Inputs!$B$14) | F9: =(Inputs!$B$4*1.1)-(Inputs!$B$5+Inputs!$B$5*Inputs!$B$6+(Inputs!$B$7*1.2)+(Inputs!$B$7*1.2)*Inputs!$B$8+Inputs!$B$10*Inputs!$B$9+(Inputs!$B$4*1.1)*Inputs!$B$11)-(Inputs!$B$12*Inputs!$B$13*Inputs!$B$9/12+Inputs!$B$12*Inputs!$B$14)
A12: COMPLETION SPREAD %
B13: Finished value →
A14: Cost to complete ↓ | B14: -0.1 | C14: -0.05 | D14: 0 | E14: 0.05 | F14: 0.1
A15: -0.1 | B15: =((Inputs!$B$4*0.9)-(Inputs!$B$5+Inputs!$B$5*Inputs!$B$6+(Inputs!$B$7*0.9)+(Inputs!$B$7*0.9)*Inputs!$B$8+Inputs!$B$10*Inputs!$B$9+(Inputs!$B$4*0.9)*Inputs!$B$11))/(Inputs!$B$5+Inputs!$B$5*Inputs!$B$6+(Inputs!$B$7*0.9)+(Inputs!$B$7*0.9)*Inputs!$B$8+Inputs!$B$10*Inputs!$B$9+(Inputs!$B$4*0.9)*Inputs!$B$11) | C15: =((Inputs!$B$4*0.95)-(Inputs!$B$5+Inputs!$B$5*Inputs!$B$6+(Inputs!$B$7*0.9)+(Inputs!$B$7*0.9)*Inputs!$B$8+Inputs!$B$10*Inputs!$B$9+(Inputs!$B$4*0.95)*Inputs!$B$11))/(Inputs!$B$5+Inputs!$B$5*Inputs!$B$6+(Inputs!$B$7*0.9)+(Inputs!$B$7*0.9)*Inputs!$B$8+Inputs!$B$10*Inputs!$B$9+(Inputs!$B$4*0.95)*Inputs!$B$11) | D15: =((Inputs!$B$4*1.0)-(Inputs!$B$5+Inputs!$B$5*Inputs!$B$6+(Inputs!$B$7*0.9)+(Inputs!$B$7*0.9)*Inputs!$B$8+Inputs!$B$10*Inputs!$B$9+(Inputs!$B$4*1.0)*Inputs!$B$11))/(Inputs!$B$5+Inputs!$B$5*Inputs!$B$6+(Inputs!$B$7*0.9)+(Inputs!$B$7*0.9)*Inputs!$B$8+Inputs!$B$10*Inputs!$B$9+(Inputs!$B$4*1.0)*Inputs!$B$11) | E15: =((Inputs!$B$4*1.05)-(Inputs!$B$5+Inputs!$B$5*Inputs!$B$6+(Inputs!$B$7*0.9)+(Inputs!$B$7*0.9)*Inputs!$B$8+Inputs!$B$10*Inputs!$B$9+(Inputs!$B$4*1.05)*Inputs!$B$11))/(Inputs!$B$5+Inputs!$B$5*Inputs!$B$6+(Inputs!$B$7*0.9)+(Inputs!$B$7*0.9)*Inputs!$B$8+Inputs!$B$10*Inputs!$B$9+(Inputs!$B$4*1.05)*Inputs!$B$11) | F15: =((Inputs!$B$4*1.1)-(Inputs!$B$5+Inputs!$B$5*Inputs!$B$6+(Inputs!$B$7*0.9)+(Inputs!$B$7*0.9)*Inputs!$B$8+Inputs!$B$10*Inputs!$B$9+(Inputs!$B$4*1.1)*Inputs!$B$11))/(Inputs!$B$5+Inputs!$B$5*Inputs!$B$6+(Inputs!$B$7*0.9)+(Inputs!$B$7*0.9)*Inputs!$B$8+Inputs!$B$10*Inputs!$B$9+(Inputs!$B$4*1.1)*Inputs!$B$11)
A16: 0 | B16: =((Inputs!$B$4*0.9)-(Inputs!$B$5+Inputs!$B$5*Inputs!$B$6+(Inputs!$B$7*1.0)+(Inputs!$B$7*1.0)*Inputs!$B$8+Inputs!$B$10*Inputs!$B$9+(Inputs!$B$4*0.9)*Inputs!$B$11))/(Inputs!$B$5+Inputs!$B$5*Inputs!$B$6+(Inputs!$B$7*1.0)+(Inputs!$B$7*1.0)*Inputs!$B$8+Inputs!$B$10*Inputs!$B$9+(Inputs!$B$4*0.9)*Inputs!$B$11) | C16: =((Inputs!$B$4*0.95)-(Inputs!$B$5+Inputs!$B$5*Inputs!$B$6+(Inputs!$B$7*1.0)+(Inputs!$B$7*1.0)*Inputs!$B$8+Inputs!$B$10*Inputs!$B$9+(Inputs!$B$4*0.95)*Inputs!$B$11))/(Inputs!$B$5+Inputs!$B$5*Inputs!$B$6+(Inputs!$B$7*1.0)+(Inputs!$B$7*1.0)*Inputs!$B$8+Inputs!$B$10*Inputs!$B$9+(Inputs!$B$4*0.95)*Inputs!$B$11) | D16: =((Inputs!$B$4*1.0)-(Inputs!$B$5+Inputs!$B$5*Inputs!$B$6+(Inputs!$B$7*1.0)+(Inputs!$B$7*1.0)*Inputs!$B$8+Inputs!$B$10*Inputs!$B$9+(Inputs!$B$4*1.0)*Inputs!$B$11))/(Inputs!$B$5+Inputs!$B$5*Inputs!$B$6+(Inputs!$B$7*1.0)+(Inputs!$B$7*1.0)*Inputs!$B$8+Inputs!$B$10*Inputs!$B$9+(Inputs!$B$4*1.0)*Inputs!$B$11) | E16: =((Inputs!$B$4*1.05)-(Inputs!$B$5+Inputs!$B$5*Inputs!$B$6+(Inputs!$B$7*1.0)+(Inputs!$B$7*1.0)*Inputs!$B$8+Inputs!$B$10*Inputs!$B$9+(Inputs!$B$4*1.05)*Inputs!$B$11))/(Inputs!$B$5+Inputs!$B$5*Inputs!$B$6+(Inputs!$B$7*1.0)+(Inputs!$B$7*1.0)*Inputs!$B$8+Inputs!$B$10*Inputs!$B$9+(Inputs!$B$4*1.05)*Inputs!$B$11) | F16: =((Inputs!$B$4*1.1)-(Inputs!$B$5+Inputs!$B$5*Inputs!$B$6+(Inputs!$B$7*1.0)+(Inputs!$B$7*1.0)*Inputs!$B$8+Inputs!$B$10*Inputs!$B$9+(Inputs!$B$4*1.1)*Inputs!$B$11))/(Inputs!$B$5+Inputs!$B$5*Inputs!$B$6+(Inputs!$B$7*1.0)+(Inputs!$B$7*1.0)*Inputs!$B$8+Inputs!$B$10*Inputs!$B$9+(Inputs!$B$4*1.1)*Inputs!$B$11)
A17: 0.1 | B17: =((Inputs!$B$4*0.9)-(Inputs!$B$5+Inputs!$B$5*Inputs!$B$6+(Inputs!$B$7*1.1)+(Inputs!$B$7*1.1)*Inputs!$B$8+Inputs!$B$10*Inputs!$B$9+(Inputs!$B$4*0.9)*Inputs!$B$11))/(Inputs!$B$5+Inputs!$B$5*Inputs!$B$6+(Inputs!$B$7*1.1)+(Inputs!$B$7*1.1)*Inputs!$B$8+Inputs!$B$10*Inputs!$B$9+(Inputs!$B$4*0.9)*Inputs!$B$11) | C17: =((Inputs!$B$4*0.95)-(Inputs!$B$5+Inputs!$B$5*Inputs!$B$6+(Inputs!$B$7*1.1)+(Inputs!$B$7*1.1)*Inputs!$B$8+Inputs!$B$10*Inputs!$B$9+(Inputs!$B$4*0.95)*Inputs!$B$11))/(Inputs!$B$5+Inputs!$B$5*Inputs!$B$6+(Inputs!$B$7*1.1)+(Inputs!$B$7*1.1)*Inputs!$B$8+Inputs!$B$10*Inputs!$B$9+(Inputs!$B$4*0.95)*Inputs!$B$11) | D17: =((Inputs!$B$4*1.0)-(Inputs!$B$5+Inputs!$B$5*Inputs!$B$6+(Inputs!$B$7*1.1)+(Inputs!$B$7*1.1)*Inputs!$B$8+Inputs!$B$10*Inputs!$B$9+(Inputs!$B$4*1.0)*Inputs!$B$11))/(Inputs!$B$5+Inputs!$B$5*Inputs!$B$6+(Inputs!$B$7*1.1)+(Inputs!$B$7*1.1)*Inputs!$B$8+Inputs!$B$10*Inputs!$B$9+(Inputs!$B$4*1.0)*Inputs!$B$11) | E17: =((Inputs!$B$4*1.05)-(Inputs!$B$5+Inputs!$B$5*Inputs!$B$6+(Inputs!$B$7*1.1)+(Inputs!$B$7*1.1)*Inputs!$B$8+Inputs!$B$10*Inputs!$B$9+(Inputs!$B$4*1.05)*Inputs!$B$11))/(Inputs!$B$5+Inputs!$B$5*Inputs!$B$6+(Inputs!$B$7*1.1)+(Inputs!$B$7*1.1)*Inputs!$B$8+Inputs!$B$10*Inputs!$B$9+(Inputs!$B$4*1.05)*Inputs!$B$11) | F17: =((Inputs!$B$4*1.1)-(Inputs!$B$5+Inputs!$B$5*Inputs!$B$6+(Inputs!$B$7*1.1)+(Inputs!$B$7*1.1)*Inputs!$B$8+Inputs!$B$10*Inputs!$B$9+(Inputs!$B$4*1.1)*Inputs!$B$11))/(Inputs!$B$5+Inputs!$B$5*Inputs!$B$6+(Inputs!$B$7*1.1)+(Inputs!$B$7*1.1)*Inputs!$B$8+Inputs!$B$10*Inputs!$B$9+(Inputs!$B$4*1.1)*Inputs!$B$11)
A18: 0.2 | B18: =((Inputs!$B$4*0.9)-(Inputs!$B$5+Inputs!$B$5*Inputs!$B$6+(Inputs!$B$7*1.2)+(Inputs!$B$7*1.2)*Inputs!$B$8+Inputs!$B$10*Inputs!$B$9+(Inputs!$B$4*0.9)*Inputs!$B$11))/(Inputs!$B$5+Inputs!$B$5*Inputs!$B$6+(Inputs!$B$7*1.2)+(Inputs!$B$7*1.2)*Inputs!$B$8+Inputs!$B$10*Inputs!$B$9+(Inputs!$B$4*0.9)*Inputs!$B$11) | C18: =((Inputs!$B$4*0.95)-(Inputs!$B$5+Inputs!$B$5*Inputs!$B$6+(Inputs!$B$7*1.2)+(Inputs!$B$7*1.2)*Inputs!$B$8+Inputs!$B$10*Inputs!$B$9+(Inputs!$B$4*0.95)*Inputs!$B$11))/(Inputs!$B$5+Inputs!$B$5*Inputs!$B$6+(Inputs!$B$7*1.2)+(Inputs!$B$7*1.2)*Inputs!$B$8+Inputs!$B$10*Inputs!$B$9+(Inputs!$B$4*0.95)*Inputs!$B$11) | D18: =((Inputs!$B$4*1.0)-(Inputs!$B$5+Inputs!$B$5*Inputs!$B$6+(Inputs!$B$7*1.2)+(Inputs!$B$7*1.2)*Inputs!$B$8+Inputs!$B$10*Inputs!$B$9+(Inputs!$B$4*1.0)*Inputs!$B$11))/(Inputs!$B$5+Inputs!$B$5*Inputs!$B$6+(Inputs!$B$7*1.2)+(Inputs!$B$7*1.2)*Inputs!$B$8+Inputs!$B$10*Inputs!$B$9+(Inputs!$B$4*1.0)*Inputs!$B$11) | E18: =((Inputs!$B$4*1.05)-(Inputs!$B$5+Inputs!$B$5*Inputs!$B$6+(Inputs!$B$7*1.2)+(Inputs!$B$7*1.2)*Inputs!$B$8+Inputs!$B$10*Inputs!$B$9+(Inputs!$B$4*1.05)*Inputs!$B$11))/(Inputs!$B$5+Inputs!$B$5*Inputs!$B$6+(Inputs!$B$7*1.2)+(Inputs!$B$7*1.2)*Inputs!$B$8+Inputs!$B$10*Inputs!$B$9+(Inputs!$B$4*1.05)*Inputs!$B$11) | F18: =((Inputs!$B$4*1.1)-(Inputs!$B$5+Inputs!$B$5*Inputs!$B$6+(Inputs!$B$7*1.2)+(Inputs!$B$7*1.2)*Inputs!$B$8+Inputs!$B$10*Inputs!$B$9+(Inputs!$B$4*1.1)*Inputs!$B$11))/(Inputs!$B$5+Inputs!$B$5*Inputs!$B$6+(Inputs!$B$7*1.2)+(Inputs!$B$7*1.2)*Inputs!$B$8+Inputs!$B$10*Inputs!$B$9+(Inputs!$B$4*1.1)*Inputs!$B$11)
A20: Gold cell = base case. Confirm the downside corner (−10% value / +20% cost) does not destroy the spread.
